project/.env
project/__init__.py
project/import/models.pkl
project/main.py
project/src/__init__.py
project/src/api.py
project/src/logger.py
project/static/fonts/CascadiaCode.woff2
project/static/index.html
project/static/license.html
project/static/scripts.js
project/static/styles.css
sillikalm-0.1.5.dist-info/METADATA
sillikalm-0.1.5.dist-info/WHEEL
sillikalm-0.1.5.dist-info/entry_points.txt
sillikalm-0.1.5.dist-info/licenses/LICENSE
sillikalm-0.1.5.dist-info/RECORD
