Metadata-Version: 2.1
Name: sillikalm
Version: 0.1.5
Summary: Silly Language Models by Allika
Keywords: LLM,Large Language Model,open-webui,ollama,sillikalm,FastAPI
Author-Email: Krishnakanth Allika <speed-acorn-whiff@duck.com>
Classifier: Development Status :: 4 - Beta
Classifier: License :: OSI Approved :: GNU General Public License v3 (GPLv3)
Classifier: Programming Language :: Python :: 3
Classifier: Programming Language :: Python :: 3.11
Classifier: Programming Language :: Python :: 3.12
Project-URL: Homepage, https://go.allika.eu.org/sillikalm
Project-URL: Repository, https://go.allika.eu.org/sillikalmrepo
Project-URL: Documentation, https://go.allika.eu.org/sillikalmdocs
Project-URL: Changelog, https://go.allika.eu.org/sillikalmchangelog
Requires-Python: <3.13,>=3.11
Requires-Dist: cryptography>=44.0.2
Requires-Dist: fastapi>=0.115.7
Requires-Dist: ollama>=0.4.7
Requires-Dist: open-webui>=0.5.20
Requires-Dist: python-dotenv>=1.0.1
Requires-Dist: uvicorn>=0.34.0
